{"ticker": "HSML11", "history": [{"date": "2019-08-01", "close": 104.58, "adj": 68.31}, {"date": "2019-09-01", "close": 102.3, "adj": 66.83}, {"date": "2019-10-01", "close": 102.5, "adj": 66.96}, {"date": "2019-11-01", "close": 109.18, "adj": 71.32}, {"date": "2019-12-01", "close": 126.03, "adj": 82.33}, {"date": "2020-01-01", "close": 121.65, "adj": 79.46}, {"date": "2020-02-01", "close": 114.72, "adj": 74.94}, {"date": "2020-03-01", "close": 82.91, "adj": 54.16}, {"date": "2020-04-01", "close": 83.26, "adj": 54.39}, {"date": "2020-05-01", "close": 82.96, "adj": 54.19}, {"date": "2020-06-01", "close": 88.74, "adj": 57.97}, {"date": "2020-07-01", "close": 85.25, "adj": 55.69}, {"date": "2020-08-01", "close": 91.51, "adj": 59.78}, {"date": "2020-09-01", "close": 92.1, "adj": 60.17}, {"date": "2020-10-01", "close": 88.2, "adj": 57.62}, {"date": "2020-11-01", "close": 92.43, "adj": 60.38}, {"date": "2020-12-01", "close": 94.02, "adj": 61.42}, {"date": "2021-01-01", "close": 97.52, "adj": 63.7}, {"date": "2021-02-01", "close": 91.75, "adj": 59.94}, {"date": "2021-03-01", "close": 87.55, "adj": 57.19}, {"date": "2021-04-01", "close": 89.59, "adj": 58.52}, {"date": "2021-05-01", "close": 90.83, "adj": 59.33}, {"date": "2021-06-01", "close": 89.14, "adj": 58.23}, {"date": "2021-07-01", "close": 86.48, "adj": 56.49}, {"date": "2021-08-01", "close": 80.76, "adj": 52.75}, {"date": "2021-09-01", "close": 79.76, "adj": 52.1}, {"date": "2021-10-01", "close": 77.12, "adj": 50.38}, {"date": "2021-11-01", "close": 69.9, "adj": 45.66}, {"date": "2021-12-01", "close": 81.36, "adj": 53.15}, {"date": "2022-01-01", "close": 75.92, "adj": 49.59}, {"date": "2022-02-01", "close": 76.78, "adj": 50.15}, {"date": "2022-03-01", "close": 81.01, "adj": 52.92}, {"date": "2022-04-01", "close": 80.52, "adj": 52.99}, {"date": "2022-05-01", "close": 80.28, "adj": 53.23}, {"date": "2022-06-01", "close": 77.76, "adj": 51.96}, {"date": "2022-07-01", "close": 78.0, "adj": 52.56}, {"date": "2022-08-01", "close": 91.13, "adj": 61.92}, {"date": "2022-09-01", "close": 93.98, "adj": 64.32}, {"date": "2022-10-01", "close": 90.74, "adj": 62.56}, {"date": "2022-11-01", "close": 81.26, "adj": 56.45}, {"date": "2022-12-01", "close": 81.6, "adj": 57.16}, {"date": "2023-01-01", "close": 79.77, "adj": 56.36}, {"date": "2023-02-01", "close": 78.56, "adj": 55.99}, {"date": "2023-03-01", "close": 79.42, "adj": 57.14}, {"date": "2023-04-01", "close": 85.04, "adj": 61.76}, {"date": "2023-05-01", "close": 87.73, "adj": 64.27}, {"date": "2023-06-01", "close": 93.33, "adj": 68.95}, {"date": "2023-07-01", "close": 94.23, "adj": 70.17}, {"date": "2023-08-01", "close": 96.22, "adj": 72.22}, {"date": "2023-09-01", "close": 93.55, "adj": 70.76}, {"date": "2023-10-01", "close": 91.41, "adj": 69.69}, {"date": "2023-11-01", "close": 93.23, "adj": 71.66}, {"date": "2023-12-01", "close": 96.47, "adj": 74.74}, {"date": "2024-01-01", "close": 96.68, "adj": 75.49}, {"date": "2024-02-01", "close": 96.94, "adj": 76.3}, {"date": "2024-03-01", "close": 98.0, "adj": 77.77}, {"date": "2024-04-01", "close": 96.75, "adj": 77.41}, {"date": "2024-05-01", "close": 96.75, "adj": 78.06}, {"date": "2024-06-01", "close": 97.35, "adj": 79.2}, {"date": "2024-07-01", "close": 96.88, "adj": 79.47}, {"date": "2024-08-01", "close": 96.55, "adj": 79.86}, {"date": "2024-09-01", "close": 92.39, "adj": 77.05}, {"date": "2024-10-01", "close": 87.16, "adj": 73.33}, {"date": "2024-11-01", "close": 82.8, "adj": 70.3}, {"date": "2024-12-01", "close": 72.91, "adj": 62.51}, {"date": "2025-01-01", "close": 73.28, "adj": 63.53}, {"date": "2025-02-01", "close": 76.7, "adj": 67.09}, {"date": "2025-03-01", "close": 83.95, "adj": 74.05}, {"date": "2025-04-01", "close": 85.86, "adj": 76.33}, {"date": "2025-05-01", "close": 85.99, "adj": 77.03}, {"date": "2025-06-01", "close": 85.31, "adj": 77.0}, {"date": "2025-07-01", "close": 79.6, "adj": 72.4}, {"date": "2025-08-01", "close": 83.0, "adj": 76.12}, {"date": "2025-09-01", "close": 86.41, "adj": 79.9}, {"date": "2025-10-01", "close": 85.88, "adj": 80.03}, {"date": "2025-11-01", "close": 88.28, "adj": 82.95}, {"date": "2025-12-01", "close": 92.54, "adj": 87.65}, {"date": "2026-01-01", "close": 92.58, "adj": 88.35}, {"date": "2026-02-01", "close": 94.72, "adj": 91.08}, {"date": "2026-03-01", "close": 95.07, "adj": 92.1}, {"date": "2026-04-01", "close": 95.77, "adj": 93.47}, {"date": "2026-05-01", "close": 92.72, "adj": 91.17}, {"date": "2026-06-01", "close": 85.7, "adj": 84.95}, {"date": "2026-06-05", "close": 90.22}, {"date": "2026-06-19", "close": 86.5, "adj": 86.5}, {"date": "2026-07-01", "close": 87.77, "adj": 87.77}, {"date": "2026-07-03", "close": 86.65, "adj": 86.65}, {"date": "2026-07-10", "close": 87.05, "adj": 87.05}, {"date": "2026-07-17", "close": 87.52, "adj": 87.52}], "updated_at": "18/07/2026 04:50"}